linkpred/__init__.py
linkpred/cli.py
linkpred/exceptions.py
linkpred/linkpred.py
linkpred/preprocess.py
linkpred/util.py
linkpred/evaluation/__init__.py
linkpred/evaluation/listeners.py
linkpred/evaluation/scoresheet.py
linkpred/evaluation/static.py
linkpred/network/__init__.py
linkpred/network/addremove.py
linkpred/network/algorithms.py
linkpred/predictors/__init__.py
linkpred/predictors/base.py
linkpred/predictors/eigenvector.py
linkpred/predictors/misc.py
linkpred/predictors/neighbour.py
linkpred/predictors/path.py
linkpred/predictors/util.py
linkpred-0.6.dist-info/entry_points.txt
linkpred-0.6.dist-info/WHEEL
linkpred-0.6.dist-info/METADATA
linkpred-0.6.dist-info/RECORD
