Metadata-Version: 2.3
Name: linkpred
Version: 0.6
Summary: linkpred, a Python package for link prediction
Author-email: Raf Guns <raf.guns@uantwerpen.be>
Requires-Python: >=3.8
Classifier: Intended Audience :: Science/Research
Classifier: Intended Audience :: Developers
Classifier: License :: OSI Approved
Classifier: Programming Language :: Python :: 3.8
Classifier: Programming Language :: Python :: 3.9
Classifier: Programming Language :: Python :: 3.10
Classifier: Programming Language :: Python :: 3.11
Classifier: Programming Language :: Python :: 3.12
Classifier: Topic :: Software Development
Classifier: Topic :: Scientific/Engineering
Classifier: Development Status :: 4 - Beta
Classifier: Natural Language :: English
Classifier: Operating System :: OS Independent
Requires-Dist: matplotlib>=3.5
Requires-Dist: networkx>=3.0
Requires-Dist: numpy>=1.23
Requires-Dist: pyyaml>=3.0
Requires-Dist: scipy>=1.10
Requires-Dist: smokesignal>=0.7
Requires-Dist: pytest >=7.1 ; extra == "all"
Requires-Dist: pytest-cov ; extra == "all"
Requires-Dist: tox>=4.4 ; extra == "all"
Requires-Dist: python-louvain ; extra == "all"
Requires-Dist: python-louvain ; extra == "community"
Requires-Dist: pytest >=7.1 ; extra == "dev"
Requires-Dist: pytest-cov ; extra == "dev"
Requires-Dist: tox>=4.4 ; extra == "dev"
Project-URL: Home, https://github.com/rafguns/linkpred/
Provides-Extra: all
Provides-Extra: community
Provides-Extra: dev
